{"contact-me_index.md":"HmHKOue3","directives_v-copy.md":"C8r7K-25","directives_v-debounce.md":"Gg0KqsbX","directives_v-noemoji.md":"Dnqc_mKu","en_contact-me_index.md":"BG3uR7Ha","en_directives_v-copy.md":"BK9vfpuh","en_directives_v-debounce.md":"DzNdMYgc","en_directives_v-noemoji.md":"SLpHT12I","en_guide_index.md":"faZ8FFBr","en_guide_installation.md":"BkRGbuoX","en_guide_quickstart.md":"CUTOiC9W","en_index.md":"DUytWl3X","guide_index.md":"DxgIBff4","guide_installation.md":"DORSPBV9","guide_quickstart.md":"CebwGguu","index.md":"BRXsFzET"}
